{
  "format_version": "1.21.20",
  "minecraft:client_entity": {
    "description": {
      "identifier": "minere:ghost",
      "materials": {
        "default": "guardian_ghost"
      },
      "textures": {
        "default": "textures/entity/minere/ghost"
      },
      "geometry": {
        "default": "geometry.minere.ghost"
      },
      "render_controllers": ["controller.render.default"],
      "spawn_egg": {
        "base_color": "#ffffff",
        "overlay_color": "#ffffff"
      },
      "scripts": {
        "animate": ["controller"]
      },
      "animations": {
        "move": "animation.minere.ghost.move",
        "attack": "animation.minere.ghost.attack",
        "look_at_target": "animation.minere.ghost.look_at_target",
        "controller": "controller.animation.minere.ghost"
      }
    }
  }
}
